llm_chat_term/__init__.py
llm_chat_term/app.py
llm_chat_term/config.py
llm_chat_term/db.py
llm_chat_term/exceptions.py
llm_chat_term/utils.py
llm_chat_term/audio/__init__.py
llm_chat_term/audio/audio_entrypoint.py
llm_chat_term/audio/pyaudio_no_log.py
llm_chat_term/audio/recorder.py
llm_chat_term/audio/speech_to_text.py
llm_chat_term/audio/voice_command.py
llm_chat_term/llm/__init__.py
llm_chat_term/llm/insert_commands.py
llm_chat_term/llm/llm_chat.py
llm_chat_term/llm/llm_client.py
llm_chat_term/llm/models.py
llm_chat_term/llm/tools/__init__.py
llm_chat_term/llm/tools/definitions.py
llm_chat_term/llm/tools/main.py
llm_chat_term/llm/tools/handlers/__init__.py
llm_chat_term/llm/tools/handlers/cat.py
llm_chat_term/llm/tools/handlers/git.py
llm_chat_term/ui/__init__.py
llm_chat_term/ui/audio_device_selector.py
llm_chat_term/ui/chat_selector.py
llm_chat_term/ui/chat_ui.py
llm_chat_term/ui/confirm_prompt.py
llm_chat_term/ui/help.py
llm_chat_term/ui/model_selector.py
llm_chat_term/ui/prompt_menu.py
llm_chat_term-0.2.12.dist-info/METADATA
llm_chat_term-0.2.12.dist-info/WHEEL
llm_chat_term-0.2.12.dist-info/entry_points.txt
llm_chat_term-0.2.12.dist-info/RECORD
