Metadata-Version: 2.4
Name: llm_chat_term
Version: 0.2.12
Summary: Chat with LLMs from the terminal
Project-URL: Homepage, https://github.com/vtsiolkas/llm_chat_term
Project-URL: Bug Tracker, https://github.com/vtsiolkas/llm_chat_term/issues
Author-email: Vasilis Tsiolkas <tsiolkas@gmail.com>
License: MIT
Classifier: Development Status :: 4 - Beta
Classifier: Environment :: Console
Classifier: License :: OSI Approved :: MIT License
Classifier: Operating System :: OS Independent
Classifier: Programming Language :: Python :: 3
Classifier: Topic :: Utilities
Requires-Python: >=3.12
Requires-Dist: langchain-anthropic>=0.3.8
Requires-Dist: langchain-deepseek>=0.1.3
Requires-Dist: langchain-google-genai>=2.1.2
Requires-Dist: langchain-openai>=0.3.7
Requires-Dist: langchain>=0.3.19
Requires-Dist: prompt-toolkit>=3.0.50
Requires-Dist: python-dotenv>=1.0.1
Requires-Dist: pyyaml>=6.0.2
Requires-Dist: rich>=13.9.4
Requires-Dist: trafilatura>=2.0.0
Provides-Extra: voice
Requires-Dist: pyaudio>=0.2.14; extra == 'voice'
Requires-Dist: pydub>=0.25.1; extra == 'voice'
